<?xml version="1.0"?>
<extension key="org.project60.sepa" type="module">
  <file>sepa</file>
  <name>SEPA Direct Debit</name>
  <description>This extension provides SEPA Direct Debit processing.</description>
  <license>aGPL3</license>
  <maintainer>
    <author>Project60</author>
    <email>endres@systopia.de</email>
  </maintainer>
  <releaseDate></releaseDate>
  <version>1.0alpha1</version>
  <develStage>alpha</develStage>
  <compatibility>
    <ver>4.4</ver>
  </compatibility>
  <comments>This module is the merge of Xaviers Dutoit's (xavier@tttp.eu) and Björn Endres' (endres@systopia.de) Project60 branches.</comments>
  <civix>
    <namespace>CRM/Sepa</namespace>
  </civix>
</extension>
